vupitap/__init__.py
vupitap/cli.py
vupitap-0.0.3.dist-info/METADATA
vupitap-0.0.3.dist-info/WHEEL
vupitap-0.0.3.dist-info/entry_points.txt
vupitap-0.0.3.dist-info/RECORD
